fpx/__init__.py
fpx/__main__.py
fpx/alembic.ini
fpx/app.py
fpx/config.py
fpx/context.py
fpx/debug_app.py
fpx/exception.py
fpx/middleware.py
fpx/model.py
fpx/pipes.py
fpx/schema.py
fpx/transport.py
fpx/types.py
fpx/utils.py
fpx/cli/__init__.py
fpx/cli/client.py
fpx/cli/db.py
fpx/cli/server.py
fpx/cli/ticket.py
fpx/migrations/README
fpx/migrations/__init__.py
fpx/migrations/env.py
fpx/migrations/script.py.mako
fpx/migrations/__pycache__/env.cpython-312.pyc
fpx/migrations/__pycache__/env.cpython-39.pyc
fpx/migrations/versions/6a22a6995723_create_clients_table.py
fpx/migrations/versions/ac8a8750d3e2_add_options_column_to_ticket_table.py
fpx/migrations/versions/ef515c12c8ff_create_tickets_table.py
fpx/migrations/versions/__pycache__/6a22a6995723_create_clients_table.cpython-312.pyc
fpx/migrations/versions/__pycache__/6a22a6995723_create_clients_table.cpython-39.pyc
fpx/migrations/versions/__pycache__/ac8a8750d3e2_add_options_column_to_ticket_table.cpython-312.pyc
fpx/migrations/versions/__pycache__/ac8a8750d3e2_add_options_column_to_ticket_table.cpython-39.pyc
fpx/migrations/versions/__pycache__/ef515c12c8ff_create_tickets_table.cpython-312.pyc
fpx/migrations/versions/__pycache__/ef515c12c8ff_create_tickets_table.cpython-39.pyc
fpx/route/__init__.py
fpx/route/stream.py
fpx/route/ticket.py
fpx/tests/__init__.py
fpx/tests/conftest.py
fpx/tests/settings.py
fpx/tests/test_model.py
fpx/tests/test_transport.py
fpx/tests/test_utils.py
fpx/tests/route/__init__.py
fpx/tests/route/test_stream.py
fpx/tests/route/test_ticket.py
fpx-0.7.0.dist-info/METADATA
fpx-0.7.0.dist-info/WHEEL
fpx-0.7.0.dist-info/entry_points.txt
fpx-0.7.0.dist-info/top_level.txt
fpx-0.7.0.dist-info/RECORD
