Metadata-Version: 2.1
Name: fpx
Version: 0.7.0
Summary: Stream archiver/proxy
Author: Sergey Motornyuk
License: AGPL
Project-URL: Homepage, https://github.com/DataShades/fpx
Classifier: Development Status :: 3 - Alpha
Classifier: License :: OSI Approved :: GNU Affero General Public License v3 or later (AGPLv3+)
Classifier: Programming Language :: Python :: 3.8
Classifier: Programming Language :: Python :: 3.9
Classifier: Programming Language :: Python :: 3.10
Classifier: Programming Language :: Python :: 3.11
Requires-Python: >=3.8
Requires-Dist: aiohttp[speedups]
Requires-Dist: alembic~=1.12.0
Requires-Dist: asyncblink==0.3.2
Requires-Dist: blinker==1.7.0
Requires-Dist: click
Requires-Dist: httpx~=0.23.0
Requires-Dist: pyjwt
Requires-Dist: sanic~=23.12.0
Requires-Dist: sanic_ext~=23.12.0
Requires-Dist: sqlalchemy~=2.0.22
Requires-Dist: typing-extensions
Requires-Dist: webargs-sanic~=2.3.5
Requires-Dist: websockets<11.0,>=10.0
Provides-Extra: postgresql
Requires-Dist: psycopg2; extra == "postgresql"
Provides-Extra: azure
Requires-Dist: azure-storage-blob; extra == "azure"
Provides-Extra: test
Requires-Dist: aioresponses; extra == "test"
Requires-Dist: factory_boy; extra == "test"
Requires-Dist: pytest; extra == "test"
Requires-Dist: pytest-asyncio; extra == "test"
Requires-Dist: pytest-factoryboy; extra == "test"
Requires-Dist: pytest-httpx; extra == "test"
Requires-Dist: sanic-testing~=23.6.0; extra == "test"
